k8t/__init__.py
k8t/__main__.py
k8t/cli.py
k8t/cluster.py
k8t/config.py
k8t/engine.py
k8t/environment.py
k8t/filters.py
k8t/project.py
k8t/scaffolding.py
k8t/secret_providers.py
k8t/templates.py
k8t/util.py
k8t/values.py
k8t/assets/configmap.yaml.j2
k8t/assets/cronjob.yaml.j2
k8t/assets/deployment.yaml.j2
k8t/assets/ingress.yaml.j2
k8t/assets/job.yaml.j2
k8t/assets/namespace.yaml.j2
k8t/assets/pod.yaml.j2
k8t/assets/secret.yaml.j2
k8t/assets/service.yaml.j2
k8t/assets/serviceaccount.yaml.j2
k8t-0.8.3.dist-info/LICENSE.txt
k8t-0.8.3.dist-info/METADATA
k8t-0.8.3.dist-info/WHEEL
k8t-0.8.3.dist-info/entry_points.txt
k8t-0.8.3.dist-info/top_level.txt
k8t-0.8.3.dist-info/RECORD
