Metadata-Version: 2.1
Name: k8t
Version: 0.8.3
Summary: Kubernetes templating engine based on Jinja2
Home-page: https://github.com/ClarkSource/k8t
Author: Aljosha Friemann
Author-email: aljosha.friemann@clark.de
Keywords: kubernetes,jinja,multi-cluster,templating
Platform: linux
Classifier: Programming Language :: Python :: 3
License-File: LICENSE.txt
Requires-Dist: Jinja2
Requires-Dist: ruamel.yaml
Requires-Dist: boto3
Requires-Dist: click
Requires-Dist: coloredlogs
Requires-Dist: simple-tools
Requires-Dist: bitmath
Provides-Extra: ujson
Requires-Dist: ujson ; extra == 'ujson'
